vtype/__init__.py
vtype/_core.py
vtype-1.1.3.dist-info/LICENSE
vtype-1.1.3.dist-info/WHEEL
vtype-1.1.3.dist-info/METADATA
vtype-1.1.3.dist-info/RECORD
