Metadata-Version: 2.1
Name: vtype
Version: 1.1.3
Summary: 一些自定义的数据类型
Keywords: vtype
Author-email: "lcctoor.com" <lcctoor@outlook.com>
Requires-Python: >=3.7
Classifier: License :: OSI Approved :: Apache Software License
Project-URL: HomePage, https://lcctoor.github.io/lccpy/?package=vtype
